{
    "images": [
        {
            "imgPath": "Images/cruise.jpg",
            "imgLocation": "Hawaii",
            "description": "Hawaii's main island coastline",
            "date": "None"
        },
        {
            "imgPath": "Images/nissankicks.jpg",
            "imgLocation": "Bermuda",
            "description": "Horseshoe Bay",
            "date": "None"
        },
        {
            "imgPath": "Images/stadiumseries.jpg",
            "imgLocation": "Bermuda Cave",
            "description": "Crystal Cave",
            "date": "05/22/2017"
        }
  ]
}